aeroapi_python/APICaller.py
aeroapi_python/AeroAPI.py
aeroapi_python/Airports.py
aeroapi_python/Flights.py
aeroapi_python/History.py
aeroapi_python/Miscellaneous.py
aeroapi_python/Operators.py
aeroapi_python/__init__.py
aeroapi_python-1.1.4.dist-info/LICENSE
aeroapi_python-1.1.4.dist-info/METADATA
aeroapi_python-1.1.4.dist-info/WHEEL
aeroapi_python-1.1.4.dist-info/top_level.txt
aeroapi_python-1.1.4.dist-info/RECORD
